sms/__init__.py
sms/__main__.py
sms/cli.py
sms/sms.py
freemobile-0.2.0.dist-info/METADATA
freemobile-0.2.0.dist-info/WHEEL
freemobile-0.2.0.dist-info/entry_points.txt
freemobile-0.2.0.dist-info/top_level.txt
freemobile-0.2.0.dist-info/RECORD
