Metadata-Version: 2.4
Name: freemobile
Version: 0.2.0
Summary: Send SMS notifications to your own mobile via any internet-connected device.
Author-email: Roman MASSE <roman@masse.family>
Maintainer-email: Roman MASSE <roman@masse.family>
License-Expression: Unlicense
Project-URL: Homepage, https://github.com/rambobinator/freemobile-SMS-notifications
Project-URL: Documentation, https://github.com/rambobinator/freemobile-SMS-notifications
Project-URL: Repository, https://github.com/rambobinator/freemobile-SMS-notifications
Project-URL: Bug Tracker, https://github.com/rambobinator/freemobile-SMS-notifications/issues
Project-URL: Changelog, https://github.com/rambobinator/freemobile-SMS-notifications/releases
Keywords: sms,free,mobile,freemobile,notification
Classifier: Intended Audience :: Developers
Classifier: Programming Language :: Python :: 3.10
Classifier: Programming Language :: Python :: 3.11
Classifier: Programming Language :: Python :: 3.12
Classifier: Programming Language :: Python :: 3.13
Classifier: Programming Language :: Python :: 3.14
Requires-Python: >=3.10
